kinesis_log_handler/__init__.py
kinesis_log_handler/firehose.py
kinesis_log_handler/version.py
kinesisloghandler-0.0.3.dist-info/LICENSE
kinesisloghandler-0.0.3.dist-info/METADATA
kinesisloghandler-0.0.3.dist-info/WHEEL
kinesisloghandler-0.0.3.dist-info/top_level.txt
kinesisloghandler-0.0.3.dist-info/RECORD
