Metadata-Version: 2.1
Name: kinesisloghandler
Version: 0.0.3
Summary: Python logging handler for sending logs to AWS Kinesis
Home-page: https://github.com/neillab/kinesisloghandler
Author: Dumok
Author-email: nsh330@gmail.com
License: BSD
Platform: UNKNOWN
Classifier: Development Status :: 3 - Alpha
Classifier: Intended Audience :: Developers
Classifier: Programming Language :: Python :: 3
Classifier: Programming Language :: Python :: 3.5
Classifier: Programming Language :: Python :: 3.6
Classifier: Topic :: System :: Logging
Requires-Python: >=3.5
Requires-Dist: boto3
